AUTHORS.rst
MANIFEST.in
README.rst
setup.py
beefycachecontrol/__init__.py
beefycachecontrol/middleware.py
beefycachecontrol/models.py
beefycachecontrol/tests/__init__.py
beefycachecontrol/tests/urls.py
beefycachecontrol/tests/views.py
django_beefycachecontrol.egg-info/PKG-INFO
django_beefycachecontrol.egg-info/SOURCES.txt
django_beefycachecontrol.egg-info/dependency_links.txt
django_beefycachecontrol.egg-info/not-zip-safe
django_beefycachecontrol.egg-info/top_level.txt