Metadata-Version: 1.0
Name: django-beefycachecontrol
Version: 0.2.1
Summary: Beefier Cache-Control HTTP headers created by @never_cache decorator in Django.
Home-page: http://github.com/tomatohater/django-beefycachecontrol
Author: Drew Engelson
Author-email: drew@engelson.net
License: BSD
Platform: UNKNOWN
Classifier: Environment :: Web Environment
Classifier: Framework :: Django
Classifier: Intended Audience :: Developers
Classifier: License :: OSI Approved :: BSD License
Classifier: Operating System :: OS Independent
Classifier: Programming Language :: Python
Classifier: Topic :: Internet :: WWW/HTTP
